hep/__init__.py
hep/epw.py
hep/idf.py
hep/idfplot.py
hep-1.0.4.dist-info/LICENSE
hep-1.0.4.dist-info/METADATA
hep-1.0.4.dist-info/WHEEL
hep-1.0.4.dist-info/top_level.txt
hep-1.0.4.dist-info/RECORD
