Metadata-Version: 2.1
Name: hep
Version: 1.0.4
Summary: Scripts to help with Energy Plus simulation.
Home-page: https://github.com/Gurgenci/hep
Author: Hal Gurgenci
Author-email: h.gurgenci@uq.edu.au
Classifier: Programming Language :: Python :: 3
Classifier: License :: OSI Approved :: GNU General Public License (GPL)
Classifier: Operating System :: OS Independent
Requires-Python: >=3.0
License-File: LICENSE
